ner_simple/__init__.py
ner_simple/ner.py
ner_simple-0.1.1.dist-info/licenses/LICENSE
ner_simple-0.1.1.dist-info/METADATA
ner_simple-0.1.1.dist-info/WHEEL
ner_simple-0.1.1.dist-info/top_level.txt
ner_simple-0.1.1.dist-info/RECORD
