Metadata-Version: 2.4
Name: ner_simple
Version: 0.1.1
Summary: A minimal package exposing a simple NER runner using Hugging Face transformers pipeline.
Author-email: Vishesh Dokania <visheshdokania77@gmail.com>
License: MIT
Keywords: ner,transformers,nlp
Classifier: Programming Language :: Python :: 3
Classifier: License :: OSI Approved :: MIT License
Classifier: Intended Audience :: Developers
Classifier: Topic :: Software Development :: Libraries
Requires-Python: >=3.8
License-File: LICENSE
Requires-Dist: transformers>=4.0
Requires-Dist: torch
Dynamic: license-file
